{
  "$schema": "https://json-schema.org/draft/2020-12/schema",
  "title": "Occupations",
  "type": "object",
  "properties": {
    "date": {
      "type": "string"
    },
    "vocab": {
      "type": "string"
    },
    "items": {
      "type": "array",
      "items": {
        "type": "object",
        "properties": {
          "id": {
            "type": "string"
          },
          "label": {
            "type": "string"
          }
        },
        "required": [
          "id",
          "label"
        ]
      }
    }
  },
  "required": [
    "items"
  ]
}
